genrat_netoc/__init__.py
genrat_netoc/main.cpython-311-darwin.so
genrat_netoc-0.1.dist-info/LICENCE.txt
genrat_netoc-0.1.dist-info/METADATA
genrat_netoc-0.1.dist-info/WHEEL
genrat_netoc-0.1.dist-info/top_level.txt
genrat_netoc-0.1.dist-info/RECORD
